{
  "gitSyncId": "fd46702b-bcd0-4881-b1cd-82dcd36b8cda_06d58a15-68da-49ca-b988-1f9045145a65",
  "id": "Page1__$JSModule101$_JSModule10.fetchData",
  "isPublic": true,
  "moduleInstanceId": "Page1_JSModule101",
  "pluginId": "js-plugin",
  "pluginType": "JS",
  "rootModuleInstanceId": "Page1_JSModule101",
  "unpublishedAction": {
    "collectionId": "Page1__$JSModule101$_JSModule10",
    "confirmBeforeExecute": false,
    "contextType": "PAGE",
    "datasource": {
      "isAutoGenerated": false,
      "name": "UNUSED_DATASOURCE",
      "pluginId": "js-plugin"
    },
    "executeOnLoad": false,
    "fullyQualifiedName": "_$JSModule101$_JSModule10.fetchData",
    "name": "fetchData",
    "pageId": "Page1",
    "userSetOnLoad": false
  }
}