{
  "gitSyncId": "fd46702b-bcd0-4881-b1cd-82dcd36b8cda_8a913bc4-940e-497a-9982-2c7487397e16",
  "id": "Page1__$JSModule41$_JSModule4.getGreeting",
  "isPublic": true,
  "moduleInstanceId": "Page1_JSModule41",
  "pluginId": "js-plugin",
  "pluginType": "JS",
  "rootModuleInstanceId": "Page1_JSModule41",
  "unpublishedAction": {
    "collectionId": "Page1__$JSModule41$_JSModule4",
    "confirmBeforeExecute": false,
    "contextType": "PAGE",
    "datasource": {
      "isAutoGenerated": false,
      "name": "UNUSED_DATASOURCE",
      "pluginId": "js-plugin"
    },
    "executeOnLoad": false,
    "fullyQualifiedName": "_$JSModule41$_JSModule4.getGreeting",
    "name": "getGreeting",
    "pageId": "Page1",
    "userSetOnLoad": false
  }
}