{
  "gitSyncId": "fd46702b-bcd0-4881-b1cd-82dcd36b8cda_c3c8ff49-4f86-4e90-ae96-bed6e6c4159a",
  "id": "Page1__$JSModule71$_JSModule7.addNumbers",
  "isPublic": true,
  "moduleInstanceId": "Page1_JSModule71",
  "pluginId": "js-plugin",
  "pluginType": "JS",
  "rootModuleInstanceId": "Page1_JSModule71",
  "unpublishedAction": {
    "collectionId": "Page1__$JSModule71$_JSModule7",
    "confirmBeforeExecute": false,
    "contextType": "PAGE",
    "datasource": {
      "isAutoGenerated": false,
      "name": "UNUSED_DATASOURCE",
      "pluginId": "js-plugin"
    },
    "executeOnLoad": false,
    "fullyQualifiedName": "_$JSModule71$_JSModule7.addNumbers",
    "name": "addNumbers",
    "pageId": "Page1",
    "userSetOnLoad": false
  }
}